bioio_tifffile/__init__.py
bioio_tifffile/reader.py
bioio_tifffile/reader_metadata.py
bioio_tifffile/utils.py
bioio_tifffile-1.3.0.dist-info/licenses/LICENSE
bioio_tifffile-1.3.0.dist-info/METADATA
bioio_tifffile-1.3.0.dist-info/WHEEL
bioio_tifffile-1.3.0.dist-info/entry_points.txt
bioio_tifffile-1.3.0.dist-info/top_level.txt
bioio_tifffile-1.3.0.dist-info/RECORD
